EEA_datasets_handler.py
EEA_datasets_handler-1.0.1.dist-info/LICENSE
EEA_datasets_handler-1.0.1.dist-info/METADATA
EEA_datasets_handler-1.0.1.dist-info/WHEEL
EEA_datasets_handler-1.0.1.dist-info/top_level.txt
EEA_datasets_handler-1.0.1.dist-info/RECORD
