Metadata-Version: 2.1
Name: EEA-datasets-handler
Version: 1.0.1
Summary: Library which handles the air pollution datasets provided by EEA
Home-page: https://github.com/EnricoPittini/EEA-datasets-handler
Author: Enrico Pittini
Author-email: pittinienrico@hotmail.it
License: MIT
Platform: UNKNOWN
Classifier: Programming Language :: Python :: 3
Classifier: License :: OSI Approved :: MIT License
Classifier: Operating System :: OS Independent
License-File: LICENSE
Requires-Dist: requests
Requires-Dist: pandas
